kv/__init__.py
kv/__init__.pyi
kv/_abc.py
kv/cli.py
kv/conn_strings.py
kv/prefix.py
kv/serialization.py
kv/tests.py
kv/impl/__init__.py
kv/impl/_dict.py
kv/impl/fs.py
kv/impl/redis.py
kv/impl/sql.py
kv/impl/azure/__init__.py
kv/impl/azure/__init__.pyi
kv/impl/azure/blob/__init__.py
kv/impl/azure/blob/blob.py
kv/impl/azure/blob/container.py
kv/impl/azure/blob/util.py
kv/impl/azure/cosmos/__init__.py
kv/impl/azure/cosmos/container.py
kv/impl/azure/cosmos/db.py
kv/impl/azure/cosmos/partition.py
kv/impl/azure/cosmos/util.py
kv/impl/http/__init__.py
kv/impl/http/__init__.pyi
kv/impl/http/client.py
kv/impl/http/server.py
python_kv-0.3.11.dist-info/METADATA
python_kv-0.3.11.dist-info/WHEEL
python_kv-0.3.11.dist-info/entry_points.txt
python_kv-0.3.11.dist-info/top_level.txt
python_kv-0.3.11.dist-info/RECORD
